aldryn_newsblog/__init__.py
aldryn_newsblog/admin.py
aldryn_newsblog/apps.py
aldryn_newsblog/cms_appconfig.py
aldryn_newsblog/cms_apps.py
aldryn_newsblog/cms_config.py
aldryn_newsblog/cms_menus.py
aldryn_newsblog/cms_plugins.py
aldryn_newsblog/cms_toolbars.py
aldryn_newsblog/cms_wizards.py
aldryn_newsblog/compat.py
aldryn_newsblog/feeds.py
aldryn_newsblog/forms.py
aldryn_newsblog/maintenance.py
aldryn_newsblog/managers.py
aldryn_newsblog/models.py
aldryn_newsblog/rendering.py
aldryn_newsblog/search_indexes.py
aldryn_newsblog/tests_settings.py
aldryn_newsblog/urls.py
aldryn_newsblog/views.py
aldryn_newsblog/locale/cs/LC_MESSAGES/django.mo
aldryn_newsblog/locale/cs/LC_MESSAGES/django.po
aldryn_newsblog/locale/de/LC_MESSAGES/django.mo
aldryn_newsblog/locale/de/LC_MESSAGES/django.po
aldryn_newsblog/locale/en/LC_MESSAGES/django.mo
aldryn_newsblog/locale/en/LC_MESSAGES/django.po
aldryn_newsblog/locale/es/LC_MESSAGES/django.mo
aldryn_newsblog/locale/es/LC_MESSAGES/django.po
aldryn_newsblog/locale/fa/LC_MESSAGES/django.mo
aldryn_newsblog/locale/fa/LC_MESSAGES/django.po
aldryn_newsblog/locale/fr/LC_MESSAGES/django.mo
aldryn_newsblog/locale/fr/LC_MESSAGES/django.po
aldryn_newsblog/locale/it/LC_MESSAGES/django.mo
aldryn_newsblog/locale/it/LC_MESSAGES/django.po
aldryn_newsblog/locale/lt/LC_MESSAGES/django.mo
aldryn_newsblog/locale/lt/LC_MESSAGES/django.po
aldryn_newsblog/locale/nl/LC_MESSAGES/django.mo
aldryn_newsblog/locale/nl/LC_MESSAGES/django.po
aldryn_newsblog/management/__init__.py
aldryn_newsblog/management/commands/__init__.py
aldryn_newsblog/management/commands/rebuild_article_search_data.py
aldryn_newsblog/migrations/0001_initial.py
aldryn_newsblog/migrations/0002_newsblogconfig_template_prefix.py
aldryn_newsblog/migrations/0003_auto_20150422_1921.py
aldryn_newsblog/migrations/0004_auto_20150622_1606.py
aldryn_newsblog/migrations/0005_auto_20150807_0207.py
aldryn_newsblog/migrations/0006_auto_20160105_1013.py
aldryn_newsblog/migrations/0007_default_newsblog_config.py
djangocms_aldryn_newsblog-4.0.3.dist-info/licenses/LICENSE.txt
djangocms_aldryn_newsblog-4.0.3.dist-info/METADATA
djangocms_aldryn_newsblog-4.0.3.dist-info/WHEEL
djangocms_aldryn_newsblog-4.0.3.dist-info/top_level.txt
djangocms_aldryn_newsblog-4.0.3.dist-info/RECORD
