Metadata-Version: 2.4
Name: djangocms-aldryn-newsblog
Version: 4.0.3
Summary: Adds blogging and newsing capabilities to django CMS.
Home-page: https://github.com/CZ-NIC/djangocms-aldryn-newsblog
Author: Divio AG
Author-email: info@divio.ch
License: BSD
Classifier: Development Status :: 5 - Production/Stable
Classifier: Environment :: Web Environment
Classifier: Intended Audience :: Developers
Classifier: License :: OSI Approved :: BSD License
Classifier: Operating System :: OS Independent
Classifier: Framework :: Django
Classifier: Framework :: Django :: 4.0
Classifier: Framework :: Django :: 5.0
Classifier: Framework :: Django CMS :: 4.1
Classifier: Framework :: Django CMS :: 5.0
Classifier: Programming Language :: Python
Classifier: Programming Language :: Python :: 3.10
Classifier: Programming Language :: Python :: 3.12
Classifier: Topic :: Internet :: WWW/HTTP
Classifier: Topic :: Internet :: WWW/HTTP :: Dynamic Content
Classifier: Topic :: Internet :: WWW/HTTP :: Dynamic Content :: News/Diary
Classifier: Topic :: Software Development
Classifier: Topic :: Software Development :: Libraries
Classifier: Topic :: Software Development :: Libraries :: Application Frameworks
Requires-Python: >=3.10
License-File: LICENSE.txt
Requires-Dist: aldryn-apphooks-config~=0.7
Requires-Dist: djangocms-aldryn-categories~=2.0
Requires-Dist: djangocms-aldryn-common~=2.0
Requires-Dist: djangocms-aldryn-people~=3.0
Requires-Dist: djangocms-aldryn-search~=3.0
Requires-Dist: djangocms-aldryn-translation-tools~=1.0
Requires-Dist: django-haystack~=3.3
Requires-Dist: backport-collections~=0.1
Requires-Dist: djangocms-text~=0.9
Requires-Dist: django-taggit~=6.1
Requires-Dist: python-dateutil~=2.9
Requires-Dist: lxml~=6.0
Requires-Dist: lxml-html-clean~=0.4
Requires-Dist: looseversion~=1.3
Dynamic: author
Dynamic: author-email
Dynamic: classifier
Dynamic: description
Dynamic: description-content-type
Dynamic: home-page
Dynamic: license
Dynamic: license-file
Dynamic: requires-dist
Dynamic: requires-python
Dynamic: summary
